torchani_step/__init__.py
torchani_step/__main__.py
torchani_step/_version.py
torchani_step/energy.py
torchani_step/energy_parameters.py
torchani_step/energy_step.py
torchani_step/installer.py
torchani_step/metadata.py
torchani_step/optimization.py
torchani_step/optimization_parameters.py
torchani_step/optimization_step.py
torchani_step/tk_energy.py
torchani_step/tk_optimization.py
torchani_step/tk_torchani.py
torchani_step/torchani.py
torchani_step/torchani_parameters.py
torchani_step/torchani_step.py
torchani_step/data/SEAMM_TorchANI.py_template
torchani_step/data/configuration.txt
torchani_step/data/properties.csv
torchani_step/data/references.bib
torchani_step/data/seamm-torchani.yml
torchani_step/data/torchani.ini
torchani_step-2025.3.10.dist-info/AUTHORS.rst
torchani_step-2025.3.10.dist-info/LICENSE
torchani_step-2025.3.10.dist-info/METADATA
torchani_step-2025.3.10.dist-info/WHEEL
torchani_step-2025.3.10.dist-info/entry_points.txt
torchani_step-2025.3.10.dist-info/top_level.txt
torchani_step-2025.3.10.dist-info/zip-safe
torchani_step-2025.3.10.dist-info/RECORD
